odoo/addons/mail_track_diff_only/README.rst
odoo/addons/mail_track_diff_only/__init__.py
odoo/addons/mail_track_diff_only/__manifest__.py
odoo/addons/mail_track_diff_only/i18n/fr.po
odoo/addons/mail_track_diff_only/i18n/mail_track_diff_only.pot
odoo/addons/mail_track_diff_only/models/__init__.py
odoo/addons/mail_track_diff_only/models/mail_thread.py
odoo/addons/mail_track_diff_only/readme/CONTRIBUTORS.rst
odoo/addons/mail_track_diff_only/readme/DESCRIPTION.rst
odoo/addons/mail_track_diff_only/readme/INSTALL.rst
odoo/addons/mail_track_diff_only/readme/USAGE.rst
odoo/addons/mail_track_diff_only/static/description/icon.png
odoo/addons/mail_track_diff_only/static/description/index.html
odoo12_addon_mail_track_diff_only-12.0.1.0.0.99.dev10.dist-info/METADATA
odoo12_addon_mail_track_diff_only-12.0.1.0.0.99.dev10.dist-info/WHEEL
odoo12_addon_mail_track_diff_only-12.0.1.0.0.99.dev10.dist-info/top_level.txt
odoo12_addon_mail_track_diff_only-12.0.1.0.0.99.dev10.dist-info/RECORD
